zoldics_service_utils/__init__.py
zoldics_service_utils/clients/__init__.py
zoldics_service_utils/clients/http_client.py
zoldics_service_utils/clients/bedrock_client/__init__.py
zoldics_service_utils/clients/bedrock_client/base_llm_operation.py
zoldics_service_utils/clients/bedrock_client/bedrock_client.py
zoldics_service_utils/clients/bedrock_client/call_bedrock.py
zoldics_service_utils/clients/bedrock_client/fm_config.py
zoldics_service_utils/clients/bedrock_client/foundation_models.py
zoldics_service_utils/clients/bedrock_client/local_interfaces_typehinter.py
zoldics_service_utils/clients/embedding_client/__init__.py
zoldics_service_utils/clients/embedding_client/bedrock_embedding_generator.py
zoldics_service_utils/clients/redis_client/__init__.py
zoldics_service_utils/clients/redis_client/async_redisclient.py
zoldics_service_utils/clients/redis_client/enums.py
zoldics_service_utils/clients/redis_client/sync_redisclient.py
zoldics_service_utils/clients/sqs_client/__init__.py
zoldics_service_utils/clients/sqs_client/helpers.py
zoldics_service_utils/clients/sqs_client/initiator.py
zoldics_service_utils/clients/sqs_client/message_handler.py
zoldics_service_utils/clients/sqs_client/polling.py
zoldics_service_utils/clients/sqs_client/post_message.py
zoldics_service_utils/clients/sqs_client/queue_config.py
zoldics_service_utils/constants/__init__.py
zoldics_service_utils/constants/errors.py
zoldics_service_utils/context/__init__.py
zoldics_service_utils/context/vars.py
zoldics_service_utils/guards/__init__.py
zoldics_service_utils/guards/guard_key_enums.py
zoldics_service_utils/guards/rate_limiter_guard.py
zoldics_service_utils/interfaces/__init__.py
zoldics_service_utils/interfaces/interfaces_pd.py
zoldics_service_utils/interfaces/interfaces_th.py
zoldics_service_utils/ioc/__init__.py
zoldics_service_utils/ioc/singleton.py
zoldics_service_utils/logging/__init__.py
zoldics_service_utils/logging/base_logger.py
zoldics_service_utils/logging/logger_decorator.py
zoldics_service_utils-0.1.16.dist-info/LICENSE
zoldics_service_utils-0.1.16.dist-info/METADATA
zoldics_service_utils-0.1.16.dist-info/WHEEL
zoldics_service_utils-0.1.16.dist-info/top_level.txt
zoldics_service_utils-0.1.16.dist-info/RECORD
