Metadata-Version: 2.2
Name: zoldics_service_utils
Version: 0.1.16
Summary: A most utile package for the governance of pythonic micro-services
Home-page: https://github.com/BRIZINGR007/PyhtonServiceUtil
Author: Nabarka_Deb
License: MIT
Requires-Python: >=3.11
License-File: LICENSE
Requires-Dist: asyncio-redis==0.16.0
Requires-Dist: redis==5.2.1
Requires-Dist: aiobotocore
Requires-Dist: boto3
Requires-Dist: PyJWT==2.8.0
Requires-Dist: jwcrypto==1.5.1
Requires-Dist: requests==2.32.3
Requires-Dist: pytz==2024.2
Requires-Dist: pydantic==2.10.5
Requires-Dist: fastapi==0.115.6
Requires-Dist: python-decouple==3.8
Requires-Dist: fastapi==0.115.6
Requires-Dist: mongoengine==0.29.1
Dynamic: author
Dynamic: description
Dynamic: description-content-type
Dynamic: home-page
Dynamic: license
Dynamic: requires-dist
Dynamic: requires-python
Dynamic: summary
